flake8_continuation.py
flake8_continuation-1.0.5.dist-info/LICENSE
flake8_continuation-1.0.5.dist-info/METADATA
flake8_continuation-1.0.5.dist-info/WHEEL
flake8_continuation-1.0.5.dist-info/entry_points.txt
flake8_continuation-1.0.5.dist-info/top_level.txt
flake8_continuation-1.0.5.dist-info/RECORD
