Metadata-Version: 2.1
Name: flake8-continuation
Version: 1.0.5
Summary: Flake8 Line Continuation Plugin
Home-page: UNKNOWN
Author: UNKNOWN
Author-email: UNKNOWN
License: Apache 2.0
Platform: UNKNOWN
Classifier: Framework :: Flake8
Classifier: Environment :: Console
Classifier: Intended Audience :: Developers
Classifier: License :: OSI Approved :: Apache Software License
Classifier: Programming Language :: Python
Classifier: Programming Language :: Python :: 2.7
Classifier: Programming Language :: Python :: 3
Classifier: Topic :: Software Development :: Libraries :: Python Modules
Classifier: Topic :: Software Development :: Quality Assurance
Provides: flake8_continuation
Requires-Dist: flake8
Requires-Dist: pycodestyle
Requires-Dist: six
